BBDecoder/__init__.py
BBDecoder/main.py
BBDecoder/analysis/__init__.py
BBDecoder/analysis/flow_architve.py
BBDecoder/analysis/grad_stats.py
BBDecoder/analysis/layer_stats.py
BBDecoder/utilities/__init__.py
BBDecoder/utilities/load_model.py
BBDecoder/utilities/similarity.py
BBDecoder/visualizer/__init__.py
BBDecoder/visualizer/custom_recorder.py
BBDecoder/visualizer/vis_main.py
BBDecoder/wrappers/__init__.py
BBDecoder/wrappers/wrapper.py
bbdecoder-1.1.1.dist-info/METADATA
bbdecoder-1.1.1.dist-info/WHEEL
bbdecoder-1.1.1.dist-info/top_level.txt
bbdecoder-1.1.1.dist-info/RECORD
