Metadata-Version: 2.4
Name: BBDecoder
Version: 1.1.1
Summary: Analysis of Pytorch Models
Author-email: Sharjeel Masood <sharjeelmasood.sm@gmail.com>, Saeed Ahmed <saeedahmad.icp@gmail.com>
Maintainer-email: Sharjeel Masood <sharjeelmasood.sm@gmail.com>, Saeed Ahmed <saeedahmad.icp@gmail.com>
License: MIT
Project-URL: homepage, https://github.com/sharjeel1999/Black-Box-Decoder
Project-URL: repository, https://github.com/sharjeel1999/Black-Box-Decoder
Keywords: pytorch,visualization,analysis,torch,deep learning,machine learning,ml,neural network
Classifier: Development Status :: 3 - Alpha
Classifier: Intended Audience :: Developers
Classifier: Intended Audience :: Science/Research
Classifier: License :: OSI Approved :: MIT License
Classifier: Programming Language :: Python
Classifier: Programming Language :: Python :: 3
Classifier: Programming Language :: Python :: 3.9
Classifier: Topic :: Scientific/Engineering :: Artificial Intelligence
Classifier: Topic :: Software Development :: Libraries :: Python Modules
Requires-Python: >=3.9
Requires-Dist: torchview>=0.2.7
Requires-Dist: graphviz
